LICENSE
MANIFEST.in
README.md
requirements.txt
setup.cfg
setup.py
mp_event_loop/__init__.py
mp_event_loop/async_event_loop.py
mp_event_loop/event_loop.py
mp_event_loop/events.py
mp_event_loop/iter_event_loop.py
mp_event_loop/mp_functions.py
mp_event_loop/mp_proxy.py
mp_event_loop.egg-info/PKG-INFO
mp_event_loop.egg-info/SOURCES.txt
mp_event_loop.egg-info/dependency_links.txt
mp_event_loop.egg-info/requires.txt
mp_event_loop.egg-info/top_level.txt