Metadata-Version: 1.1
Name: mp-event-loop
Version: 1.2.4
Summary: Library for long running multiprocessing event loops.
Home-page: https://github.com/justengel/mp_event_loop
Author: Justin Engel
Author-email: jtengel08@gmail.com
License: MIT
Download-URL: https://github.com/justengel/mp_event_loop/archive/v1.2.4.tar.gz
Keywords: multiprocessing,event,loop,event loop,process
Platform: any
Classifier: Programming Language :: Python
Classifier: Programming Language :: Python :: 3
Classifier: Operating System :: OS Independent
